LICENSE
MANIFEST.in
setup.py
DataPreprocessPack/__init__.py
DataPreprocessPack/__version__.py
DataPreprocessPack.egg-info/PKG-INFO
DataPreprocessPack.egg-info/SOURCES.txt
DataPreprocessPack.egg-info/dependency_links.txt
DataPreprocessPack.egg-info/requires.txt
DataPreprocessPack.egg-info/top_level.txt
DataPreprocessPack/toolbox/__init__.py
DataPreprocessPack/toolbox/v1/Method_DiscreteDenoise.py
DataPreprocessPack/toolbox/v1/Method_NanFill.py
DataPreprocessPack/toolbox/v1/Method_TimestampAlign.py
DataPreprocessPack/toolbox/v1/__init__.py
DataPreprocessPack/validation/__init__.py
DataPreprocessPack/validation/v1/Validation_DiscreteDenoise.py
DataPreprocessPack/validation/v1/Validation_NanFill.py
DataPreprocessPack/validation/v1/Validation_TimestampAlign.py
DataPreprocessPack/validation/v1/__init__.py