Metadata-Version: 2.1
Name: DataPreprocessPack
Version: 0.1.0
Summary: 数据预处理方法库
Home-page: https://github.com/zhaozl1123/DataPreprocessPack
Author: zhaozl1123
Author-email: 545362989@qq.com
License: MIT
Platform: UNKNOWN
Classifier: License :: OSI Approved :: MIT License
Classifier: Programming Language :: Python
Classifier: Programming Language :: Python :: 3
Classifier: Programming Language :: Python :: 3.6
Classifier: Programming Language :: Python :: Implementation :: CPython
Classifier: Programming Language :: Python :: Implementation :: PyPy
Requires-Python: >=3.7.0
License-File: LICENSE
